incrementer.py
incrementer-1.0.2.dist-info/LICENSE
incrementer-1.0.2.dist-info/WHEEL
incrementer-1.0.2.dist-info/METADATA
incrementer-1.0.2.dist-info/RECORD
