Metadata-Version: 2.1
Name: incrementer
Version: 1.0.2
Summary: 分布式主键生成器，支持多机器|多进程|多线程并发生成。
Keywords: incrementer,increment
Author-email: 江南雨上 <lcctoor@outlook.com>
Classifier: License :: OSI Approved :: Apache Software License
Requires-Dist: arts>=2024.7.29
Project-URL: Source, https://github.com/lcctoor/arts/tree/main/arts/incrementer
